sphinx_click_custom/__init__.py
sphinx_click_custom/ext.py
sphinx_click_custom-0.3.0.dist-info/licenses/LICENSE
sphinx_click_custom-0.3.0.dist-info/WHEEL
sphinx_click_custom-0.3.0.dist-info/METADATA
sphinx_click_custom-0.3.0.dist-info/RECORD
